MANIFEST.in
README.rst
TITLE.txt
lh-agpl3-LICENSE.txt
setup.py
./bin/bx-bases-bsif.py
bsif/__init__.py
bsif.bashDist.egg-info/PKG-INFO
bsif.bashDist.egg-info/SOURCES.txt
bsif.bashDist.egg-info/dependency_links.txt
bsif.bashDist.egg-info/namespace_packages.txt
bsif.bashDist.egg-info/not-zip-safe
bsif.bashDist.egg-info/requires.txt
bsif.bashDist.egg-info/top_level.txt
bsif/bashDist/__init__.py
bsif/bashDist/thisPkg.py
bsif/bashDist-config/placeHolderForFPs
bsif/bashDist-root/bin/bsrApache2Cap.sh
bsif/bashDist-root/bin/bystarApache2Admin.sh
bsif/bashDist-root/bin/lcaApache2Admin.sh
bsif/bashDist-root/bin/lcaApache2BinsPrep.sh
bsif/bashDist-root/bin/mmaApacheBinsPrep.sh
bsif/bashDist-root/bin/mmaApachePlusBinsPrep.sh
bsif/bashDist-root/lib/doLib.sh